timebox/__init__.py
timebox/constants.py
timebox/exceptions.py
timebox/timebox.py
timebox/timebox_tag.py
timebox/pandasio/__init__.py
timebox/pandasio/pandabar.py
timebox/pandasio/pandabarexceptions.py
timebox/pandasio/pandacage.py
timebox/pandasio/pandacage_exceptions.py
timebox/tests/__init__.py
timebox/tests/test_tag_string_name.py
timebox/tests/test_timebox_data_io.py
timebox/tests/test_timebox_dates.py
timebox/tests/test_timebox_file_info.py
timebox/tests/test_timebox_io.py
timebox/tests/test_timebox_pandas.py
timebox/tests/test_timebox_tag.py
timebox/tests/test_timebox_tag_compression.py
timebox/utils/__init__.py
timebox/utils/binary.py
timebox/utils/datetime_utils.py
timebox/utils/exceptions.py
timebox/utils/numpy_utils.py
timebox/utils/pandas_utils.py
timebox/utils/validation.py
timebox/utils/tests/__init__.py
timebox/utils/tests/test_binary.py
timebox/utils/tests/test_datetime_utils.py
timebox/utils/tests/test_numpy_compression.py
timebox/utils/tests/test_numpy_decompression.py
timebox/utils/tests/test_numpy_float_compression.py
timebox/utils/tests/test_numpy_utils.py
timebox/utils/tests/test_pandas_utils.py
timebox/utils/tests/test_validation.py
timebox-0.0.5.dist-info/METADATA
timebox-0.0.5.dist-info/RECORD
timebox-0.0.5.dist-info/WHEEL
timebox-0.0.5.dist-info/top_level.txt
