Metadata-Version: 2.1
Name: timebox
Version: 0.0.5
Summary: An IO library for pandas
Home-page: https://github.com/briankopp/timebox
Author: Brian Kopp
Author-email: briankopp.usa@gmail.com
License: UNKNOWN
Platform: UNKNOWN
Requires-Dist: numpy
Requires-Dist: pandas
Requires-Dist: python-dateutil
Requires-Dist: pytz
Requires-Dist: six
